mnemos/__init__.py
mnemos/core.py
mnemos/models.py
mnemos/store/base.py
mnemos/store/memory.py
mnemos-0.1.1.dist-info/LICENSE
mnemos-0.1.1.dist-info/METADATA
mnemos-0.1.1.dist-info/WHEEL
mnemos-0.1.1.dist-info/RECORD
