Metadata-Version: 2.3
Name: mnemos
Version: 0.1.1
Summary: Memory for agentic AI. Inspired by the brain. Built for the future.
License: MIT
Author: Tyson Chan
Author-email: tyson.chan@proton.me
Requires-Python: >=3.12,<3.13
Classifier: License :: OSI Approved :: MIT License
Classifier: Programming Language :: Python :: 3
Classifier: Programming Language :: Python :: 3.12
